leo/__init__.py
leo/cli.py
leo/clicontext.py
leo/enums.py
leo/helper.py
leo/package_files/mleapsparkmodel.py.dist
leo/package_files/spark_util.py.dist
leo/template/cli_template.jinja2
leo/template/config.py.jinja2
leo/template/data.py.jinja2
leo/template/docker-compose.yml.jinja2
leo/template/index.rst.jinja2
leo/template/kong_setup_service.sh.jinja2
leo/template/model_template.jinja2
leo/template/prometheus.yml.jinja2
leo/template/readme.jinja2
leo/template/requirements.txt.jinja2
leo/template/schema_template.jinja2
leo/template/tests.jinja2
leo/template/train.py.jinja2
leo/template/__pycache__/__init__.cpython-37.pyc
leo/template/__pycache__/template.cpython-37.pyc
leo/template/api/falcon.jinja2
leo/template/api/falcon_init.jinja2
leo/template/api/flask.jinja2
leo/template/api/flask_init.jinja2
leo/template/dockerfile/normal.jinja2
leo/template/dockerfile/spark.jinja2
leo/template/elk/elasticsearch.yml.jinja2
leo/template/elk/kibana.yml.jinja2
leo/template/elk/logstash.conf.jinja2
leo/template/elk/logstash.yml.jinja2
leo/template/grafana/grafana.ini.jinja2
leo/template/grafana/graphite_dashboard.json.jinja2
leo/template/grafana/graphite_source.yaml.jinja2
leo/template/grafana/prometheus_dashboard.json.jinja2
leo/template/grafana/prometheus_source.yaml.jinja2
leo/template/grafana/provisioning.yaml.jinja2
leo/template/graphite/aggregation-rules.conf.jinja2
leo/template/graphite/carbon.conf.jinja2
leo/template/graphite/relay-rules.conf.jinja2
leo/template/graphite/rewrite-rules.conf.jinja2
leo/template/graphite/storage-aggregation.conf.jinja2
leo/template/graphite/storage-schemas.conf.jinja2
leo/template/kubernetes/db_pod_template.yml.jinja2
leo/template/kubernetes/db_service.yml.jinja2
leo/template/kubernetes/elastic_pod_template.yml.jinja2
leo/template/kubernetes/elastic_service.yml.jinja2
leo/template/kubernetes/grafana_pod_template.yml.jinja2
leo/template/kubernetes/grafana_service.yml.jinja2
leo/template/kubernetes/graphite_pod_template.yml.jinja2
leo_python-0.0.5.dist-info/LICENSE
leo_python-0.0.5.dist-info/METADATA
leo_python-0.0.5.dist-info/WHEEL
leo_python-0.0.5.dist-info/entry_points.txt
leo_python-0.0.5.dist-info/top_level.txt
leo_python-0.0.5.dist-info/RECORD
